{
  "transactions": [
    {
      "amount": 1000.0,
      "category": "Income",
      "description": "Income from Home Money",
      "timestamp": "2024-08-20 08:15:00",
      "transaction_type": "income",
      "source": "Home Money"
    },
    {
      "amount": -40.0,
      "category": "Snack",
      "description": "Coffee",
      "timestamp": "2024-08-20 08:15",
      "transaction_type": "expense",
      "source": null
    }
  ],
  "expense_breakdown": {
    "Snack": {
      "total": -40.0,
      "transactions": [
        {
          "amount": -40.0,
          "category": "Snack",
          "description": "Coffee",
          "timestamp": "2024-08-20 08:15",
          "transaction_type": "expense",
          "source": null
        }
      ]
    }
  },
  "main_income_balance": 960.0,
  "budgets": {}
}